[
{"product_name": "VW Overrunning Alternator Pulley Clutch INA VOLKSWAGEN Top Quality Replacement"},
{"product_name": "MERCEDES SPRINTER 903 2.1D Gear Change Cable 00 to 06 5 Speed MTM Firstline New"},
{"product_name": "Ball Joint fits MINI COOPER 1.6 Front Lower, Left or Right, Outer 01 to 06 New"},
{"product_name": "Air Intake Control Valve 7.00326.03.0 Pierburg 55354158 5860854 Quality New"},
{"product_name": "VAUXHALL VIVARO X83 Pollen / Cabin Filter 2.0 2.0D 01 to 14 B&B 4408840 91160128"},
{"product_name": "2x Wiper Blades (Pair) Flat / Aero type A860S Bosch Set Windscreen 3AC955425 New"},
{"product_name": "Fuel Filter BFF8000 Borg & Beck 3C0127177 ACD8090E Genuine Quality Replacement"},
{"product_name": "Water Pump KCP2078 Key Parts Coolant 1334145 1334166 24469102 95507589 90542606"},
{"product_name": "HT Leads Ignition Cables Set 0986357208 Bosch 1110740 1110741 1110742 1110743"},
{"product_name": "Fuel Pressure regulator 0280160575 Bosch Control Valve 078133534C BA9C968B New"},
{"product_name": "2x Wiper Blades (Pair) Flat / Aero type fits TOYOTA RAV-4 Front 2.0 2.4 3.5 2.2D"},
{"product_name": "Lambda Sensor 0258006127 Bosch Oxygen MHK100840 MHK100840L A117E6007F LSF42 New"},
{"product_name": "AUDI A4 8E, 8H, B7 2x Wiper Blades (Pair) Flat / Aero type Front 03 to 09 Set"},
{"product_name": "2x Wiper Blades (Pair) Flat / Aero type 3397009023 Bosch Set Windscreen A208S"},
{"product_name": "2x Wiper Blades (Pair) Flat / Aero type 3397009016 Bosch Set Windscreen A016S"},
{"product_name": "VAUXHALL INSIGNIA A Pollen / Cabin Filter 08 to 17 B&B 13271191 1808246 13503675"},
{"product_name": "Fuel Filter F026402836 Bosch A6420903152 A6420904852 A6420905352 A6420906052 New"},
{"product_name": "FORD MONDEO Mk3 2.0 HT Leads Ignition Cables Set 00 to 07 Genuine Bosch New"},
{"product_name": "2x Wiper Blades (Pair) Flat / Aero type 3397007639 Bosch Set Windscreen A639S"},
{"product_name": "FORD CAPRI Mk3 2.8 Accelerator Cable 81 to 87 PRN Throttle FirstLine 6083095 New"},
{"product_name": "PEUGEOT 206 1.4 Clutch Cable 1998 on B&B 2150EF 2150X5 Top Quality Replacement"},
{"product_name": "SAAB 900 2.0 Clutch Concentric Slave Cylinder CSC 78 to 90 Manual Central B&B"},
{"product_name": "AUDI A6 4F Air Filter 2.0 2.0D 04 to 11 Bosch 4F0133843A Top Quality Replacement"},
{"product_name": "CV Joint Boot Kit fits NISSAN X-TRAIL T30 2.2D Front Inner, Left 01 to 07 C.V."},
{"product_name": "LAND ROVER FREELANDER L359 2.2D Overrunning Alternator Pulley 06 to 14 Clutch"},
{"product_name": "2x Wiper Blades (Pair) Flat / Aero type 3397007221 Bosch Set Windscreen 93183143"},
{"product_name": "Air Filter fits NISSAN QASHQAI J11 1.5D 2013 on K9K Bosch 165464BA1A Quality New"},
{"product_name": "Clutch Cable fits KIA PICANTO SA 1.1 04 to 07 G4HG B&B 4151007900 Quality New"},
{"product_name": "2x Wiper Blades (Pair) Flat / Aero type 3397014205 Bosch Set Windscreen A205S"},
{"product_name": "2x Wiper Blades (Pair) Flat / Aero type 3397118980 Bosch Set Windscreen A980S"},
{"product_name": "Oil Filter F026407072 Bosch 11427805707 11427807177 P7072 Quality Replacement"},
{"product_name": "Bump Stop fits KIA SORENTO Mk1 2.4 Rear 02 to 09 G4JS Suspension 551513E001 Febi"},
{"product_name": "PEUGEOT Oil Filter B&B Genuine Top Quality Replacement New"},
{"product_name": "MAP Sensor 0281006076 Bosch Manifold Pressure 045962101F 45962101F 55568175 New"},
{"product_name": "CITROEN DS5 2.0D Dip Stick 11 to 15 Oil 1174G9 1174G1 1174F0 Febi Quality New"},
{"product_name": "Ignition Coil 0221122349 Bosch 211905115D 00061 Genuine Top Quality Replacement"},
{"product_name": "MERCEDES SPRINTER 906 2.1D Diesel Particulate Filter DPF 2006 on 338969RMP Soot"},
{"product_name": "Spark Plugs Set 4x 0242140512 Bosch A0041594403 A0041594903 A0041595803 Quality"},
{"product_name": "Rocker Cover Gasket fits BMW Z4 E85 2.0 05 to 07 N46B20B BGA Quality Replacement"},
{"product_name": "Pollen / Cabin Filter 1987435097 Bosch 971332H001 971332H001AT 97133F2000 M5097"},
{"product_name": "Oil Cooler 31168 NRF Radiator 038117021B 038117021C 038117021D 038117021E New"},
{"product_name": "Lambda Sensor F00HL00193 Bosch Oxygen 639806 LS27 LS50193 F00HL00091 Quality New"},
{"product_name": "Air Filter F026400347 Bosch PE071313DA PE07133A0A PE7W133A0 MA5620 S0347 Quality"},
{"product_name": "Radiator Hose 05-3042 Gates Coolant C2S5369 1X438B273AD Top Quality Replacement"},
{"product_name": "Water Pump fits DAIHATSU HIJET S85 1.3 1998 on HCE Coolant B&B Quality New"},
{"product_name": "Pure/Lt 499 H7 12v 55w Px26d (X2) 1987301406 Bosch H7 12V55WH7PURELI"},
{"product_name": "Air Filter F026400365 Bosch 13717800151 S0365 Genuine Top Quality Replacement"},
{"product_name": "Spark Plugs Set 4x 0242129512 Bosch 12120034677 12120035933 5960A5 5960L0 New"},
{"product_name": "MERCEDES C220 S204, W204 2.1D Interior Blower Motor 07 to 14 Heater NRF Quality"},
{"product_name": "2x Wiper Blades (Pair) Flat / Aero type 3397118949 Bosch Set Windscreen A949S"}
][
{"apel": "orko"},
{"apel": "orko"},
{"apel": "orko"},
{"apel": "orko"},
{"apel": "orko"},
{"apel": "orko"},
{"apel": "orko"},
{"apel": "orko"},
{"apel": "orko"},
{"apel": "orko"},
{"apel": "orko"},
{"apel": "orko"},
{"apel": "orko"},
{"apel": "orko"},
{"apel": "orko"},
{"apel": "orko"},
{"apel": "orko"},
{"apel": "orko"},
{"apel": "orko"},
{"apel": "orko"},
{"apel": "orko"},
{"apel": "orko"},
{"apel": "orko"},
{"apel": "orko"},
{"apel": "orko"},
{"apel": "orko"},
{"apel": "orko"},
{"apel": "orko"},
{"apel": "orko"},
{"apel": "orko"},
{"apel": "orko"},
{"apel": "orko"},
{"apel": "orko"},
{"apel": "orko"},
{"apel": "orko"},
{"apel": "orko"},
{"apel": "orko"},
{"apel": "orko"},
{"apel": "orko"},
{"apel": "orko"},
{"apel": "orko"},
{"apel": "orko"},
{"apel": "orko"},
{"apel": "orko"},
{"apel": "orko"},
{"apel": "orko"},
{"apel": "orko"},
{"apel": "orko"},
{"apel": "orko"},
{"apel": "orko"}
]